CHANGES.txt
README.txt
bootstrap.py
buildout.cfg
setup.cfg
setup.py
src/plone/__init__.py
src/plone.recipe.atcontenttypes.egg-info/PKG-INFO
src/plone.recipe.atcontenttypes.egg-info/SOURCES.txt
src/plone.recipe.atcontenttypes.egg-info/dependency_links.txt
src/plone.recipe.atcontenttypes.egg-info/entry_points.txt
src/plone.recipe.atcontenttypes.egg-info/namespace_packages.txt
src/plone.recipe.atcontenttypes.egg-info/not-zip-safe
src/plone.recipe.atcontenttypes.egg-info/requires.txt
src/plone.recipe.atcontenttypes.egg-info/top_level.txt
src/plone/recipe/__init__.py
src/plone/recipe/atcontenttypes/__init__.py