Metadata-Version: 1.0
Name: plone.recipe.atcontenttypes
Version: 0.2
Summary: ZC Buildout recipe to generate an ATContentTypes configuration file in the etc/ folder of a zope instance
Home-page: http://dev.plone.org/collective/browser/buildout/plone.recipe.atcontenttypes
Author: Kevin Deldycke
Author-email: kev@coolcavemen.com
License: ZPL 2.1
Keywords: zope buildout ATContentTypes recipe plone ATContentTypes.configuration.zconf
Platform: UNKNOWN
Classifier: License :: OSI Approved :: Zope Public License
Classifier: Framework :: Buildout
Classifier: Framework :: Plone
Classifier: Framework :: Zope2
Classifier: Framework :: Zope3
Classifier: Programming Language :: Python
